README.rst
setup.py
xyq/__init__.py
xyq.egg-info/PKG-INFO
xyq.egg-info/SOURCES.txt
xyq.egg-info/dependency_links.txt
xyq.egg-info/requires.txt
xyq.egg-info/top_level.txt